noetry/__main__.py
noetry-1.0.0.dist-info/METADATA
noetry-1.0.0.dist-info/WHEEL
noetry-1.0.0.dist-info/entry_points.txt
noetry-1.0.0.dist-info/top_level.txt
noetry-1.0.0.dist-info/RECORD
